{
  "KazanMall": 175,
  "Авиапарк": 608,
  "Автозаводец": 10,
  "Акварель Волгоград": 197,
  "Алмаз Челябинск": 155,
  "Аура": 204,
  "Аура Ярославль": 171,
  "Галерея Краснодар": 218,
  "Галерея Новосибирск": 167,
  "Галерея Санкт-Петербург": 317,
  "Ганза": 83,
  "Горизонт Ростов": 273,
  "Град Воронеж": 114,
  "Жар-Птица": 194,
  "Золотая Миля": 86,
  "Индиго": 66,
  "Кристалл Тюмень": 175,
  "Крым": 60,
  "МЕГА Нижний Новгород": 142,
  "МореМолл": 183,
  "Небо": 154,
  "Океанис": 92,
  "Павелецкий Плаза": 162,
  "Парк Авеню": 40,
  "Планета Красноярск": 231,
  "Планета Уфа": 204,
  "РИО": 106,
  "Седьмое небо": 145,
  "Счастье": 43,
  "Фантастика": 222
}